pysswordsz/ChineseWords.py
pysswordsz/__init__.py
pysswordsz/__main__.py
pysswordsz/app.py
pysswordsz/encrytool.py
pysswordsz/getrandwords.py
pysswordsz/pwsmanager.py
pysswordsz/pzsconfig.py
pysswordsz-0.2.8.dist-info/METADATA
pysswordsz-0.2.8.dist-info/WHEEL
pysswordsz-0.2.8.dist-info/entry_points.txt
pysswordsz-0.2.8.dist-info/licenses/LICENSE
pysswordsz-0.2.8.dist-info/RECORD
