Metadata-Version: 2.3
Name: pysswordsz
Version: 0.2.8
Summary: A password manager in Python that not only manages passwords but also serves as a simple encryption software.
Project-URL: Homepage, https://github.com/SidneyLYZhang/pysswordSz
Project-URL: Repository, https://github.com/SidneyLYZhang/pysswordSz
Project-URL: Issues, https://github.com/SidneyLYZhang/pysswordSz/issues
Author-email: SidneyZhang <zly@lyzhang.me>
License:                     GNU GENERAL PUBLIC LICENSE
License-File: LICENSE
Requires-Python: >=3.8
Requires-Dist: numpy>=2.0.1
Requires-Dist: polars>=1.3.0
Requires-Dist: pycryptodome>=3.20.0
Requires-Dist: pyperclip>=1.9.0
Requires-Dist: pypinyin>=0.52.0
Requires-Dist: pywubi>=0.0.2
Requires-Dist: pyyaml>=6.0.1
Requires-Dist: randomwords>=0.4.0
Requires-Dist: typer>=0.12.3
